MHDataLearn/__init__.py
MHDataLearn/modelselector/__init__.py
MHDataLearn/modelselector/default_models.py
MHDataLearn/modelselector/model_selector.py
MHDataLearn/preprocessing/__init__.py
MHDataLearn/preprocessing/calculate.py
MHDataLearn/preprocessing/clean.py
MHDataLearn/preprocessing/load.py
MHDataLearn/preprocessing/process.py
MHDataLearn-1.1.22.dist-info/LICENSE
MHDataLearn-1.1.22.dist-info/METADATA
MHDataLearn-1.1.22.dist-info/WHEEL
MHDataLearn-1.1.22.dist-info/top_level.txt
MHDataLearn-1.1.22.dist-info/RECORD
