Metadata-Version: 2.1
Name: MHDataLearn
Version: 1.1.22
Summary: A package to preprocess raw Mental Health Services Data Sets (MHSDS), apply classification machine learning algorithmsand select the best performing using algorithm metrics
Home-page: UNKNOWN
Author: Kris Bennett, Samuel Nyeko, Kuang Myat wai yan YanSimon Wellesley Miller
Author-email: UNKNOWN
License: UNKNOWN
Platform: UNKNOWN
Requires-Dist: numpy (>=1.14.0)
Requires-Dist: pandas (>=1.0.0)
Requires-Dist: matplotlib (>=3.2.0)
Requires-Dist: seaborn (>=0.9.1)
Requires-Dist: scikit-learn (>=0.22.1)
Requires-Dist: pytest (>=6.0.0)
